cart/__init__.py
cart/admin.py
cart/apps.py
cart/models.py
cart/views.py
cart/migrations/0001_initial.py
cart/migrations/__init__.py
dj_cart-1.0.0.dist-info/LICENSE
dj_cart-1.0.0.dist-info/METADATA
dj_cart-1.0.0.dist-info/WHEEL
dj_cart-1.0.0.dist-info/top_level.txt
dj_cart-1.0.0.dist-info/RECORD
