Metadata-Version: 2.1
Name: dj-cart
Version: 1.0.0
Summary: A simple shopping cart for Django.
Home-page: https://github.com/iyanuashiri/dj-cart
Maintainer: Iyanuoluwa Ajao
Maintainer-email: ajaoiyanu@gmail.com
License: MIT
Platform: UNKNOWN
Classifier: Development Status :: 5 - Production/Stable
Classifier: Environment :: Web Environment
Classifier: Framework :: Django
Classifier: Intended Audience :: Developers
Classifier: License :: OSI Approved :: MIT License
Classifier: Operating System :: OS Independent
Classifier: Programming Language :: Python
Classifier: Programming Language :: Python :: 3
Classifier: Programming Language :: Python :: 3.6
Classifier: Topic :: Software Development :: Libraries :: Python Modules
Requires-Dist: Django (>=1.1)
